LICENSE
README.rst
setup.cfg
setup.py
bwplot/__about__.py
bwplot/__init__.py
bwplot/colors.py
bwplot/line_styles.py
bwplot/markers.py
bwplot/tools.py
bwplot.egg-info/PKG-INFO
bwplot.egg-info/SOURCES.txt
bwplot.egg-info/dependency_links.txt
bwplot.egg-info/not-zip-safe
bwplot.egg-info/requires.txt
bwplot.egg-info/top_level.txt