Metadata-Version: 2.1
Name: bwplot
Version: 0.2.26
Summary: A package to prepare a plot for black and white printing
Home-page: https://github.com/eng-tools/bwplot
Author: Maxim Millen
Author-email: mmi46@uclive.ac.nz
License: MIT
Platform: UNKNOWN
Classifier: Development Status :: 3 - Alpha
Classifier: Intended Audience :: Science/Research
Classifier: Topic :: Scientific/Engineering
Classifier: License :: OSI Approved :: MIT License
Classifier: Programming Language :: Python :: 3
Provides-Extra: test
License-File: LICENSE
